sec2md/__init__.py
sec2md/absolute_table_parser.py
sec2md/chunking.py
sec2md/core.py
sec2md/models.py
sec2md/parser.py
sec2md/section_extractor.py
sec2md/sections.py
sec2md/table_parser.py
sec2md/utils.py
sec2md/chunker/__init__.py
sec2md/chunker/blocks.py
sec2md/chunker/chunk.py
sec2md/chunker/chunker.py
sec2md-0.1.15.dist-info/licenses/LICENSE
sec2md-0.1.15.dist-info/METADATA
sec2md-0.1.15.dist-info/WHEEL
sec2md-0.1.15.dist-info/top_level.txt
sec2md-0.1.15.dist-info/RECORD
