Metadata-Version: 2.4
Name: sec2md
Version: 0.1.15
Summary: Convert SEC EDGAR filings to LLM-ready Markdown for AI agents and agentic RAG
Author-email: Lucas Astorian <lucas@intellifin.ai>
License: MIT
Project-URL: Homepage, https://github.com/lucasastorian/sec2md
Project-URL: Repository, https://github.com/lucasastorian/sec2md
Project-URL: Issues, https://github.com/lucasastorian/sec2md/issues
Keywords: sec,edgar,markdown,filings,10-k,10-q,llm,rag,ai,embeddings
Classifier: Development Status :: 3 - Alpha
Classifier: Intended Audience :: Developers
Classifier: Intended Audience :: Financial and Insurance Industry
Classifier: License :: OSI Approved :: MIT License
Classifier: Programming Language :: Python :: 3
Classifier: Programming Language :: Python :: 3.9
Classifier: Programming Language :: Python :: 3.10
Classifier: Programming Language :: Python :: 3.11
Classifier: Programming Language :: Python :: 3.12
Classifier: Topic :: Office/Business :: Financial
Classifier: Topic :: Text Processing :: Markup :: Markdown
Requires-Python: >=3.9
License-File: LICENSE
Requires-Dist: beautifulsoup4>=4.12.0
Requires-Dist: lxml>=4.9.0
Requires-Dist: requests>=2.31.0
Requires-Dist: tiktoken>=0.5.0
Requires-Dist: pydantic>=2.0.0
Provides-Extra: dev
Requires-Dist: pytest>=7.0.0; extra == "dev"
Requires-Dist: pytest-cov>=4.0.0; extra == "dev"
Requires-Dist: black>=23.0.0; extra == "dev"
Requires-Dist: ruff>=0.1.0; extra == "dev"
Dynamic: license-file
